pulp_rpm/__init__.py
pulp_rpm/pytest_plugin.py
pulp_rpm/app/__init__.py
pulp_rpm/app/access_policy.py
pulp_rpm/app/advisory.py
pulp_rpm/app/comps.py
pulp_rpm/app/constants.py
pulp_rpm/app/depsolving.py
pulp_rpm/app/downloaders.py
pulp_rpm/app/exceptions.py
pulp_rpm/app/fields.py
pulp_rpm/app/modelresource.py
pulp_rpm/app/modulemd.py
pulp_rpm/app/replica.py
pulp_rpm/app/rpm_version.py
pulp_rpm/app/settings.py
pulp_rpm/app/shared_utils.py
pulp_rpm/app/urls.py
pulp_rpm/app/kickstart/__init__.py
pulp_rpm/app/kickstart/treeinfo.py
pulp_rpm/app/management/__init__.py
pulp_rpm/app/management/commands/__init__.py
pulp_rpm/app/management/commands/rpm-datarepair.py
pulp_rpm/app/management/commands/rpm-repository-storage-analysis.py
pulp_rpm/app/management/commands/rpm-trim-changelogs.py
pulp_rpm/app/migrations/0001_initial.py
pulp_rpm/app/migrations/0001_squashed_0062_rpmpackagesigningservice_and_more.py
pulp_rpm/app/migrations/0002_updaterecord_reboot_suggested.py
pulp_rpm/app/migrations/0003_DATA_incorrect_json.py
pulp_rpm/app/migrations/0004_add_metadata_signing_service_fk.py
pulp_rpm/app/migrations/0005_optimize_sync.py
pulp_rpm/app/migrations/0006_opensuse_support.py
pulp_rpm/app/migrations/0007_checksum_types.py
pulp_rpm/app/migrations/0008_advisory_pkg_sumtype_as_int.py
pulp_rpm/app/migrations/0009_revision_null.py
pulp_rpm/app/migrations/0010_revision_null_redo.py
pulp_rpm/app/migrations/0011_rpmremote_sles_auth_token.py
pulp_rpm/app/migrations/0012_remove_pkg_group_env_cat_related_pkgs.py
pulp_rpm/app/migrations/0013_RAW_rpm_evr_extension.py
pulp_rpm/app/migrations/0014_rpmrepository_package_retention_policy.py
pulp_rpm/app/migrations/0015_repo_metadata.py
pulp_rpm/app/migrations/0016_dist_tree_nofk.py
pulp_rpm/app/migrations/0017_merge_advisory_collections.py
pulp_rpm/app/migrations/0018_updatecollection__update_record.py
pulp_rpm/app/migrations/0019_migrate_updatecollection_data.py
pulp_rpm/app/migrations/0020_remove_updatecollection_m2m.py
pulp_rpm-3.34.0.dist-info/licenses/LICENSE
pulp_rpm-3.34.0.dist-info/METADATA
pulp_rpm-3.34.0.dist-info/WHEEL
pulp_rpm-3.34.0.dist-info/entry_points.txt
pulp_rpm-3.34.0.dist-info/top_level.txt
pulp_rpm-3.34.0.dist-info/RECORD
